lazr/__init__.py
lazr/postgresql/__init__.py
lazr/postgresql/connectionstring.py
lazr/postgresql/migrate.py
lazr/postgresql/quoting.py
lazr/postgresql/upgrade.py
lazr/postgresql/tests/__init__.py
lazr/postgresql/tests/test_migrate.py
lazr/postgresql/tests/test_upgrade.py
lazr.postgresql-0.0.4.dist-info/DESCRIPTION.rst
lazr.postgresql-0.0.4.dist-info/METADATA
lazr.postgresql-0.0.4.dist-info/RECORD
lazr.postgresql-0.0.4.dist-info/WHEEL
lazr.postgresql-0.0.4.dist-info/entry_points.txt
lazr.postgresql-0.0.4.dist-info/metadata.json
lazr.postgresql-0.0.4.dist-info/top_level.txt
