Metadata-Version: 2.0
Name: lazr.postgresql
Version: 0.0.4
Summary: LAZR postgresql specific support code.
Home-page: https://launchpad.net/lazr-postgresql
Maintainer: Launchpad Developers
Maintainer-email: launchpad-dev@lists.launchpad.net
License: UNKNOWN
Platform: UNKNOWN
Classifier: Development Status :: 2 - Pre-Alpha
Classifier: Intended Audience :: Developers
Classifier: License :: OSI Approved :: GNU General Public License (GPL)
Classifier: Operating System :: OS Independent
Classifier: Programming Language :: Python
Classifier: Programming Language :: Python :: 2.7
Classifier: Programming Language :: Python :: 3
Provides-Extra: test
Provides-Extra: test
Requires-Dist: fixtures; extra == 'test'
Requires-Dist: testtools; extra == 'test'
Requires-Dist: van.pg; extra == 'test'
